setup.py
url_extractor/__init__.py
url_extractor/url_extractor.py
url_extractor.egg-info/PKG-INFO
url_extractor.egg-info/SOURCES.txt
url_extractor.egg-info/dependency_links.txt
url_extractor.egg-info/top_level.txt