Metadata-Version: 1.0
Name: url-extractor
Version: 0.0.2
Summary: extract the domain from a url
Home-page: http://mikolaje.github.io
Author: dennis
Author-email: xfl1991@gmail.com
License: MIT Licence
Keywords: pip,url_extractor,dennis
Platform: any
